find_julia/__init__.py
find_julia/_find.py
find_julia/_jill.py
find_julia/install_julia.py
find_julia/julia_version.py
find_julia/juliaup.py
find_julia/util.py
find_julia-0.2.9.dist-info/LICENSE.md
find_julia-0.2.9.dist-info/METADATA
find_julia-0.2.9.dist-info/WHEEL
find_julia-0.2.9.dist-info/top_level.txt
find_julia-0.2.9.dist-info/RECORD
