Metadata-Version: 2.1
Name: find-julia
Version: 0.2.9
Summary: Find or install Julia
License: MIT
Project-URL: Home, http://github.com/jlapeyre/find_julia
Platform: UNKNOWN
Classifier: Framework :: Django
Classifier: License :: OSI Approved :: MIT License
Classifier: Programming Language :: Python :: 3
License-File: LICENSE.md
Requires-Dist: julia-semver
Requires-Dist: jill
